{
    "$schema": "http://json-schema.org/draft-07/schema",
    "$id": "http://example.com/example.json",
    "type": "object",
    "title": "The Root Schema",
    "description": "The root schema comprises the entire JSON document.",
    "required": [
        "stageName",
        "constructionId"
    ],
    "properties": {
        "stageName": {
            "$id": "#/properties/stageName",
            "type": "string",
            "title": "The stageName Schema",
            "description": "Nome da etapa",
            "minLength": 3,
            "maxLength": 50,
            "default": "",
            "examples": [
                "string"
            ]
        },
        "constructionId": {
            "$id": "#/properties/constructionId",
            "type": "number",
            "title": "The constructionId Schema",
            "description": "ID da construção",
            "default": "",
            "examples": [
                0
            ]
        }
    },
    "additionalProperties": true
}
